hatena_cli/__init__.py
hatena_cli/__main__.py
hatena_cli/api.py
hatena_cli/auth.py
hatena_cli/cli.py
hatena_cli/config.py
hatena_cli/main.py
hatena_cli-1.0.1.dist-info/LICENSE
hatena_cli-1.0.1.dist-info/METADATA
hatena_cli-1.0.1.dist-info/WHEEL
hatena_cli-1.0.1.dist-info/entry_points.txt
hatena_cli-1.0.1.dist-info/RECORD
