Metadata-Version: 2.1
Name: hatena-cli
Version: 1.0.1
Summary: 
Author: Taichi Maeda
Author-email: taichi.maeda.up@gmail.com
Requires-Python: >=3.11,<4.0
Classifier: Programming Language :: Python :: 3
Classifier: Programming Language :: Python :: 3.11
Requires-Dist: beautifulsoup4 (>=4.12.2,<5.0.0)
Requires-Dist: flatdict (>=4.0.1,<5.0.0)
Requires-Dist: lxml (>=4.9.2,<5.0.0)
Requires-Dist: requests (>=2.31.0,<3.0.0)
Requires-Dist: requests-oauthlib (>=1.3.1,<2.0.0)
Requires-Dist: toml (>=0.10.2,<0.11.0)
Requires-Dist: typer[all] (>=0.9.0,<0.10.0)
Requires-Dist: typing-extensions (>=4.7.0,<5.0.0)
